README.rst
setup.py
nlp/__init__.py
nlp/chatbot/__init__.py
nlp/chatbot/decode_conv.py
nlp/chatbot/model.py
nlp/chatbot/run.py
nlp/chatbot/test.py
nlp/chatbot/train.py
nlp/chatbot/dataset/__init__.py
nlp/chatbot/dataset/data_utils.py
nlp/crf/__init__.py
nlp/crf/crf.py
nlp/ner/__init__.py
nlp/ner/idcnn/__init__.py
nlp/ner/idcnn/conlleval.py
nlp/ner/idcnn/loader.py
nlp/ner/idcnn/model.py
nlp/ner/idcnn/predict.py
nlp/ner/idcnn/run.py
nlp/ner/idcnn/train.py
nlp/ner/idcnn/utils.py
nlp/ner/idcnn/dataset/__init__.py
nlp/ner/idcnn/dataset/batch_manager.py
nlp/ner/idcnn/dataset/data_utils.py
nlp/ner/lstm/__init__.py
nlp/ner/lstm/bilstm_model.py
nlp/ner/lstm/model.py
nlp/ner/lstm/predict.py
nlp/ner/lstm/run.py
nlp/ner/lstm/train.py
nlp/ner/lstm/dataset/__init__.py
nlp/ner/lstm/dataset/dataset.py
nlp/ner/lstm/dataset/rawdata.py
nlp/poems/__init__.py
nlp/poems/generate.py
nlp/poems/model.py
nlp/poems/run.py
nlp/poems/train.py
nlp/poems/dataset/__init__.py
nlp/poems/dataset/poems.py
nlp/pos/__init__.py
nlp/pos/idcnn/__init__.py
nlp/pos/lstm/__init__.py
nlp/pos/lstm/bilstm_model.py
nlp/pos/lstm/model.py
nlp/pos/lstm/predict.py
nlp/pos/lstm/run.py
nlp/pos/lstm/train.py
nlp/pos/lstm/dataset/__init__.py
nlp/pos/lstm/dataset/dataset.py
nlp/pos/lstm/dataset/rawdata.py
nlp/relation_extract/__init__.py
nlp/relation_extract/model.py
nlp/relation_extract/run.py
nlp/relation_extract/test.py
nlp/relation_extract/train.py
nlp/relation_extract/dataset/__init__.py
nlp/relation_extract/dataset/utils.py
nlp/segment/__init__.py
nlp/segment/idcnn/__init__.py
nlp/segment/joint_bilstm_crf/__init__.py
nlp/segment/joint_bilstm_crf/batch.py
nlp/segment/joint_bilstm_crf/evaluation.py
nlp/segment/joint_bilstm_crf/layers.py
nlp/segment/joint_bilstm_crf/losses.py
nlp/segment/joint_bilstm_crf/model.py
nlp/segment/joint_bilstm_crf/run.py
nlp/segment/joint_bilstm_crf/test.py
nlp/segment/joint_bilstm_crf/train.py
nlp/segment/joint_bilstm_crf/dataset/__init__.py
tensorflow_nlp.egg-info/PKG-INFO
tensorflow_nlp.egg-info/SOURCES.txt
tensorflow_nlp.egg-info/dependency_links.txt
tensorflow_nlp.egg-info/requires.txt
tensorflow_nlp.egg-info/top_level.txt