Metadata-Version: 1.1
Name: tensorflow-nlp
Version: 0.0.1
Summary: Deep Learning NLP Tasks implemented on Tensorflow
Home-page: https://github.com/koala-ai/tensorflow_nlp
Author: endymecy
Author-email: endymecy@sina.cn
License: Apache License 2.0
Keywords: DeepLearning Chinese-NLP Tensorflow Koala-ai
Platform: UNKNOWN
Classifier: Development Status :: 4 - Beta
Classifier: Programming Language :: Python :: 3
Classifier: Topic :: Scientific/Engineering
Classifier: Topic :: Software Development
Classifier: Topic :: Scientific/Engineering :: Artificial Intelligence
